odoo/addons/hr_expense_petty_cash/README.rst
odoo/addons/hr_expense_petty_cash/__init__.py
odoo/addons/hr_expense_petty_cash/__manifest__.py
odoo/addons/hr_expense_petty_cash/i18n/hr_expense_petty_cash.pot
odoo/addons/hr_expense_petty_cash/i18n/it.po
odoo/addons/hr_expense_petty_cash/models/__init__.py
odoo/addons/hr_expense_petty_cash/models/account_move.py
odoo/addons/hr_expense_petty_cash/models/hr_expense.py
odoo/addons/hr_expense_petty_cash/models/hr_expense_sheet.py
odoo/addons/hr_expense_petty_cash/models/petty_cash.py
odoo/addons/hr_expense_petty_cash/readme/CONFIGURE.rst
odoo/addons/hr_expense_petty_cash/readme/CONTRIBUTORS.rst
odoo/addons/hr_expense_petty_cash/readme/DESCRIPTION.rst
odoo/addons/hr_expense_petty_cash/readme/USAGE.rst
odoo/addons/hr_expense_petty_cash/security/ir.model.access.csv
odoo/addons/hr_expense_petty_cash/static/description/icon.png
odoo/addons/hr_expense_petty_cash/static/description/index.html
odoo/addons/hr_expense_petty_cash/tests/__init__.py
odoo/addons/hr_expense_petty_cash/tests/test_hr_expense_petty_cash.py
odoo/addons/hr_expense_petty_cash/views/account_move_views.xml
odoo/addons/hr_expense_petty_cash/views/hr_expense_sheet_views.xml
odoo/addons/hr_expense_petty_cash/views/hr_expense_views.xml
odoo/addons/hr_expense_petty_cash/views/petty_cash_views.xml
odoo14_addon_hr_expense_petty_cash-14.0.1.0.1.dist-info/METADATA
odoo14_addon_hr_expense_petty_cash-14.0.1.0.1.dist-info/WHEEL
odoo14_addon_hr_expense_petty_cash-14.0.1.0.1.dist-info/top_level.txt
odoo14_addon_hr_expense_petty_cash-14.0.1.0.1.dist-info/RECORD
